tcp_tls_tunnel/__init__.py
tcp_tls_tunnel/constants.py
tcp_tls_tunnel/create_tunnel_connection.py
tcp_tls_tunnel/dto.py
tcp_tls_tunnel/exceptions.py
tcp_tls_tunnel/httpx_adapter.py
tcp_tls_tunnel/hyper_http2_adapter.py
tcp_tls_tunnel/requests_adapter.py
tcp_tls_tunnel/utils.py
tcp_tls_tunnel-1.0.2.dist-info/LICENCE
tcp_tls_tunnel-1.0.2.dist-info/METADATA
tcp_tls_tunnel-1.0.2.dist-info/WHEEL
tcp_tls_tunnel-1.0.2.dist-info/top_level.txt
tcp_tls_tunnel-1.0.2.dist-info/RECORD
