Metadata-Version: 2.1
Name: tcp-tls-tunnel
Version: 1.0.2
Summary: TCP TLS tunnel for HTTP requests with HTTP2 support.
Home-page: https://github.com/Virtual-Shard/tcp-tls-tunnel-py
License: MIT
Platform: UNKNOWN
Classifier: License :: OSI Approved :: MIT License
Classifier: Programming Language :: Python :: 3
Classifier: Programming Language :: Python :: 3.7
License-File: LICENCE
Provides-Extra: httpx
Requires-Dist: h2 (<5.0,>=4.0) ; extra == 'httpx'
Requires-Dist: httpx (>=0.18.2) ; extra == 'httpx'
Provides-Extra: hyper
Requires-Dist: h2 (<3.0,>=2.6.2) ; extra == 'hyper'
Requires-Dist: hpack (<4.0,>=3.0.0) ; extra == 'hyper'
Requires-Dist: hyper (<0.8.0,>=0.7.0) ; extra == 'hyper'
